primary/__init__.py
primary/data_analysis.py
primary_data_analysis-0.0.5.dist-info/METADATA
primary_data_analysis-0.0.5.dist-info/WHEEL
primary_data_analysis-0.0.5.dist-info/top_level.txt
primary_data_analysis-0.0.5.dist-info/RECORD
