Metadata-Version: 2.1
Name: primary-data-analysis
Version: 0.0.5
Summary: Primary data analysis for pandas dataframe
Home-page: https://github.com/anagha-bhople/primary_data_analysis
Author: Anagha Bhople
Author-email: bhoplea34@gmail.com
License: MIT
Keywords: data analysis eda pandas
Platform: UNKNOWN
Requires-Dist: matplotlib
Requires-Dist: numpy
Requires-Dist: pandas
Requires-Dist: plotly
Requires-Dist: seaborn
Requires-Dist: setuptools
Requires-Dist: six
Requires-Dist: sklearn
Requires-Dist: statsmodels
